daric/.DS_Store
daric/__init__.py
daric/data/.DS_Store
daric/data/__init__.py
daric/data/hg19_chrom.size.txt
daric/data/hg19_gap.bed
daric/data/hg38_chrom.size.txt
daric/data/hg38_gap.bed
daric/data/mm10_chrom.size.txt
daric/data/mm10_gap.bed
daric/data/mm9_chrom.size.txt
daric/data/mm9_gap.bed
daric/lib/.DS_Store
daric/lib/__init__.py
daric/lib/calculation.py
daric/lib/hmm.py
daric/lib/normalization.py
daric/main.py
daric-0.2.20.dist-info/entry_points.txt
daric-0.2.20.dist-info/LICENSE
daric-0.2.20.dist-info/WHEEL
daric-0.2.20.dist-info/METADATA
daric-0.2.20.dist-info/RECORD
