Metadata-Version: 2.1
Name: daric
Version: 0.2.20
Summary: DARIC, a computational framework to find quantitatively differential compartments from Hi-C data
Author: Yan Kai
Author-email: smilekai@gwmail.gwu.edu
Requires-Python: >=3.8,<3.11
Classifier: Programming Language :: Python :: 3
Classifier: Programming Language :: Python :: 3.10
Classifier: Programming Language :: Python :: 3.8
Classifier: Programming Language :: Python :: 3.9
Requires-Dist: HTSeq (>=0.12.4,<0.13.0)
Requires-Dist: hmmlearn (>=0.2.6,<0.3.0)
Requires-Dist: matplotlib (==3.3.4)
Requires-Dist: numpy (>=1.20.1,<2.0.0)
Requires-Dist: pandas (>=1.4.1,<2.0.0)
Requires-Dist: pyBigWig (>=0.3.18,<0.4.0)
Requires-Dist: scikit-learn (>=1.0.2,<2.0.0)
Requires-Dist: scipy (>=1.6.2,<2.0.0)
Requires-Dist: seaborn (>=0.11.1,<0.12.0)
Requires-Dist: typer[all] (>=0.4.1,<0.5.0)
